extra_platforms/__init__.py
extra_platforms/_deprecated.py
extra_platforms/_types.py
extra_platforms/_utils.py
extra_platforms/architecture_data.py
extra_platforms/ci_data.py
extra_platforms/detection.py
extra_platforms/group.py
extra_platforms/group_data.py
extra_platforms/operations.py
extra_platforms/platform_data.py
extra_platforms/py.typed
extra_platforms/pytest.py
extra_platforms/trait.py
extra_platforms-7.0.0.dist-info/licenses/license
extra_platforms-7.0.0.dist-info/WHEEL
extra_platforms-7.0.0.dist-info/entry_points.txt
extra_platforms-7.0.0.dist-info/METADATA
extra_platforms-7.0.0.dist-info/RECORD
