Metadata-Version: 2.4
Name: extra-platforms
Version: 7.0.0
Summary: 🔎 Detect architectures, platforms, and CI systems, grouped by family
Keywords: ALT Linux,Amazon Linux,Android,Arch Linux,Architecture detection,ARM (32-bit),ARM64 (AArch64),ARMv5TE (little-endian),ARMv6 (little-endian),ARMv7 (little-endian),ARMv8 (32-bit, little-endian),AT&T System Five,Azure Pipelines,Bamboo,Buildkite,Buildroot,CachyOS,CentOS,Circle CI,Cirrus CI,CloudLinux OS,CodeBuild,Cygwin,Debian,DragonFly BSD,Exherbo Linux,Fedora,FreeBSD,Gentoo Linux,GitHub Actions runner,GitLab CI,GNU/Hurd,Guix System,Haiku,Heroku CI,IBM AIX,IBM PowerKVM,IBM z/Architecture 
Author: Kevin Deldycke
Author-email: Kevin Deldycke <kevin@deldycke.com>
License-File: license
Classifier: Development Status :: 5 - Production/Stable
Classifier: Environment :: Console
Classifier: Environment :: MacOS X
Classifier: Environment :: WebAssembly
Classifier: Environment :: WebAssembly :: Emscripten
Classifier: Environment :: WebAssembly :: WASI
Classifier: Environment :: Win32 (MS Windows)
Classifier: Framework :: Pytest
Classifier: Intended Audience :: Developers
Classifier: License :: OSI Approved :: GNU General Public License v2 or later (GPLv2+)
Classifier: Operating System :: Android
Classifier: Operating System :: BeOS
Classifier: Operating System :: MacOS
Classifier: Operating System :: MacOS :: MacOS 9
Classifier: Operating System :: MacOS :: MacOS X
Classifier: Operating System :: Microsoft
Classifier: Operating System :: Microsoft :: MS-DOS
Classifier: Operating System :: Microsoft :: Windows
Classifier: Operating System :: Microsoft :: Windows :: Windows 3.1 or Earlier
Classifier: Operating System :: Microsoft :: Windows :: Windows 7
Classifier: Operating System :: Microsoft :: Windows :: Windows 8
Classifier: Operating System :: Microsoft :: Windows :: Windows 8.1
Classifier: Operating System :: Microsoft :: Windows :: Windows 10
Classifier: Operating System :: Microsoft :: Windows :: Windows 11
Classifier: Operating System :: Microsoft :: Windows :: Windows 95/98/2000
Classifier: Operating System :: Microsoft :: Windows :: Windows CE
Classifier: Operating System :: Microsoft :: Windows :: Windows NT/2000
Classifier: Operating System :: Microsoft :: Windows :: Windows Server 2003
Classifier: Operating System :: Microsoft :: Windows :: Windows Server 2008
Classifier: Operating System :: Microsoft :: Windows :: Windows Vista
Classifier: Operating System :: Microsoft :: Windows :: Windows XP
Classifier: Operating System :: OS Independent
Classifier: Operating System :: OS/2
Classifier: Operating System :: Other OS
Classifier: Operating System :: PDA Systems
Classifier: Operating System :: POSIX
Classifier: Operating System :: POSIX :: AIX
Classifier: Operating System :: POSIX :: BSD
Classifier: Operating System :: POSIX :: BSD :: BSD/OS
Classifier: Operating System :: POSIX :: BSD :: FreeBSD
Classifier: Operating System :: POSIX :: BSD :: NetBSD
Classifier: Operating System :: POSIX :: BSD :: OpenBSD
Classifier: Operating System :: POSIX :: GNU Hurd
Classifier: Operating System :: POSIX :: HP-UX
Classifier: Operating System :: POSIX :: IRIX
Classifier: Operating System :: POSIX :: Linux
Classifier: Operating System :: POSIX :: Other
Classifier: Operating System :: POSIX :: SCO
Classifier: Operating System :: POSIX :: SunOS/Solaris
Classifier: Operating System :: PalmOS
Classifier: Operating System :: RISC OS
Classifier: Operating System :: Unix
Classifier: Operating System :: iOS
Classifier: Programming Language :: Python :: 3
Classifier: Programming Language :: Python :: 3.10
Classifier: Programming Language :: Python :: 3.11
Classifier: Programming Language :: Python :: 3.12
Classifier: Programming Language :: Python :: 3.13
Classifier: Programming Language :: Python :: 3.14
Classifier: Programming Language :: Python :: Implementation :: CPython
Classifier: Topic :: Software Development :: Libraries :: Python Modules
Classifier: Topic :: System :: Hardware
Classifier: Topic :: System :: Operating System
Classifier: Topic :: System :: Operating System Kernels
Classifier: Topic :: System :: Operating System Kernels :: BSD
Classifier: Topic :: System :: Operating System Kernels :: GNU Hurd
Classifier: Topic :: System :: Operating System Kernels :: Linux
Classifier: Topic :: Utilities
Classifier: Typing :: Typed
Requires-Dist: distro>=1.9.0
Requires-Dist: pytest>=8.2.1 ; extra == 'pytest'
Requires-Python: >=3.10
Project-URL: Changelog, https://github.com/kdeldycke/extra-platforms/blob/main/changelog.md
Project-URL: Documentation, https://kdeldycke.github.io/extra-platforms
Project-URL: Download, https://github.com/kdeldycke/extra-platforms/releases/tag/v7.0.0
Project-URL: Funding, https://github.com/sponsors/kdeldycke
Project-URL: Homepage, https://github.com/kdeldycke/extra-platforms
Project-URL: Issues, https://github.com/kdeldycke/extra-platforms/issues
Project-URL: Repository, https://github.com/kdeldycke/extra-platforms
Provides-Extra: pytest
